{
  "total-play-time-ms": 35900339,
  "username": "simplex",
  "password": "123456",
  "email": "null",
  "staff-rights": "DEVELOPER",
  "game-mode": "NORMAL",
  "loyalty-title": "SKILLER",
  "position": {
    "x": 3139,
    "y": 3781,
    "z": 0
  },
  "online-status": "ON",
  "given-starter": false,
  "money-pouch": 0,
  "donated": 0,
  "minutes-bonus-exp": -1,
  "total-gained-exp": 300340103,
  "barrows-points": 0,
  "member-points": 0,
  "prestige-points": 0,
  "achievement-points": 9,
  "dung-tokens": 0,
  "commendations": 0,
  "loyalty-points": 9918,
  "total-loyalty-points": 9917.0,
  "voting-points": 0,
  "slayer-points": 0,
  "pk-points": 0,
  "player-kills": 0,
  "player-killstreak": 0,
  "player-deaths": 0,
  "target-percentage": 100,
  "bh-rank": 0,
  "gender": "MALE",
  "spell-book": "ANCIENT",
  "prayer-book": "CURSES",
  "running": true,
  "run-energy": 100,
  "music": false,
  "sounds": false,
  "auto-retaliate": true,
  "xp-locked": false,
  "veng-cast": false,
  "last-veng": 1454680938225,
  "fight-type": "WARHAMMER_POUND",
  "sol-effect": 0,
  "skull-timer": 0,
  "accept-aid": false,
  "poison-damage": 0,
  "poison-immunity": 0,
  "overload-timer": 0,
  "fire-immunity": 0,
  "fire-damage-mod": 0,
  "prayer-renewal-timer": 0,
  "teleblock-timer": 0,
  "special-amount": 100,
  "entered-gwd-room": false,
  "gwd-altar-delay": 0,
  "gwd-killcount": [
    0,
    0,
    0,
    0
  ],
  "effigy": 0,
  "summon-npc": -1,
  "summon-death": -1,
  "process-farming": false,
  "clanchat": "null",
  "autocast": false,
  "autocast-spell": -1,
  "dfs-charges": 0,
  "coins-gambled": 0,
  "slayer-master": "VANNAKA",
  "slayer-task": "NO_TASK",
  "prev-slayer-task": "NO_TASK",
  "task-amount": 0,
  "task-streak": 0,
  "duo-partner": "null",
  "double-slay-xp": false,
  "recoil-deg": 0,
  "brawlers-deg": [
    0,
    0,
    0,
    0,
    0,
    0,
    0,
    0,
    0,
    0,
    0
  ],
  "killed-players": [],
  "killed-gods": [
    false,
    false,
    false,
    false,
    false
  ],
  "barrows-brother": [
    [
      2030,
      0
    ],
    [
      2029,
      0
    ],
    [
      2028,
      0
    ],
    [
      2027,
      0
    ],
    [
      2026,
      0
    ],
    [
      2025,
      0
    ]
  ],
  "random-coffin": 0,
  "barrows-killcount": 0,
  "nomad": [
    true,
    false
  ],
  "recipe-for-disaster": [
    false,
    false,
    false,
    false,
    false,
    false,
    false,
    false,
    false
  ],
  "recipe-for-disaster-wave": 0,
  "clue-progress": 0,
  "dung-items-bound": [
    0,
    0,
    0,
    0,
    0
  ],
  "rune-ess": 0,
  "pure-ess": 0,
  "has-bank-pin": false,
  "last-pin-attempt": 0,
  "invalid-pin-attempts": 0,
  "bank-pin": [
    0,
    0,
    0,
    0
  ],
  "appearance": [
    0,
    3,
    18,
    26,
    34,
    38,
    42,
    14,
    2,
    14,
    5,
    4,
    0
  ],
  "agility-obj": [
    false,
    true,
    true,
    true,
    true,
    false,
    false
  ],
  "skills": {
    "level": [
      99,
      9999,
      9999,
      9135,
      99,
      0,
      99,
      99,
      99,
      99,
      99,
      99,
      99,
      99,
      99,
      99,
      99,
      99,
      99,
      99,
      99,
      99,
      99,
      99,
      99
    ],
    "maxLevel": [
      99,
      9999,
      9999,
      9999,
      99,
      990,
      99,
      99,
      99,
      99,
      99,
      99,
      99,
      99,
      99,
      99,
      99,
      99,
      99,
      99,
      99,
      99,
      99,
      99,
      99
    ],
    "experience": [
      179720356,
      545051716,
      536870911,
      647935069,
      14259652,
      13034431,
      17560777,
      13034431,
      13034431,
      13034431,
      13034431,
      13034431,
      13034431,
      13036321,
      13034431,
      13034431,
      13034431,
      13034431,
      13034431,
      13034431,
      13034431,
      13034431,
      13034431,
      13034431,
      13034431
    ]
  },
  "inventory": [
    {
      "id": 13049,
      "amount": 1,
      "slot": 0
    },
    {
      "id": 18357,
      "amount": 1,
      "slot": 0
    },
    {
      "id": 4755,
      "amount": 1,
      "slot": 0
    },
    {
      "id": 13740,
      "amount": 1,
      "slot": 0
    },
    {
      "id": 10499,
      "amount": 1,
      "slot": 0
    },
    {
      "id": 19908,
      "amount": 1,
      "slot": 0
    },
    {
      "id": 13045,
      "amount": 1,
      "slot": 0
    },
    {
      "id": 9244,
      "amount": 495,
      "slot": 0
    },
    {
      "id": 11230,
      "amount": 499,
      "slot": 0
    },
    {
      "id": 12934,
      "amount": 51,
      "slot": 0
    },
    {
      "id": 13576,
      "amount": 1,
      "slot": 0
    },
    {
      "id": 12926,
      "amount": 1,
      "slot": 0
    },
    {
      "id": 20555,
      "amount": 1,
      "slot": 0
    },
    {
      "id": 3749,
      "amount": 1,
      "slot": 0
    },
    {
      "id": 22047,
      "amount": 1,
      "slot": 0
    },
    {
      "id": 22010,
      "amount": 1,
      "slot": 0
    },
    {
      "id": -1,
      "amount": 0,
      "slot": 0
    },
    {
      "id": 11732,
      "amount": 1,
      "slot": 0
    },
    {
      "id": 22011,
      "amount": 1,
      "slot": 0
    },
    {
      "id": 13045,
      "amount": 1,
      "slot": 0
    },
    {
      "id": -1,
      "amount": 0,
      "slot": 0
    },
    {
      "id": -1,
      "amount": 0,
      "slot": 0
    },
    {
      "id": -1,
      "amount": 0,
      "slot": 0
    },
    {
      "id": -1,
      "amount": 0,
      "slot": 0
    },
    {
      "id": -1,
      "amount": 0,
      "slot": 0
    },
    {
      "id": -1,
      "amount": 0,
      "slot": 0
    },
    {
      "id": -1,
      "amount": 0,
      "slot": 0
    },
    {
      "id": -1,
      "amount": 0,
      "slot": 0
    }
  ],
  "equipment": [
    {
      "id": -1,
      "amount": 0,
      "slot": 0
    },
    {
      "id": -1,
      "amount": 0,
      "slot": 0
    },
    {
      "id": 15126,
      "amount": 1,
      "slot": 0
    },
    {
      "id": 13045,
      "amount": 1,
      "slot": 0
    },
    {
      "id": 2503,
      "amount": 1,
      "slot": 0
    },
    {
      "id": -1,
      "amount": 0,
      "slot": 0
    },
    {
      "id": -1,
      "amount": 0,
      "slot": 0
    },
    {
      "id": 2497,
      "amount": 1,
      "slot": 0
    },
    {
      "id": -1,
      "amount": 0,
      "slot": 0
    },
    {
      "id": 7462,
      "amount": 1,
      "slot": 0
    },
    {
      "id": 22012,
      "amount": 1,
      "slot": 0
    },
    {
      "id": -1,
      "amount": 0,
      "slot": 0
    },
    {
      "id": 15019,
      "amount": 1,
      "slot": 0
    },
    {
      "id": -1,
      "amount": 0,
      "slot": 0
    }
  ],
  "preset-equipment": [
    {
      "id": -1,
      "amount": 0,
      "slot": 0
    },
    {
      "id": -1,
      "amount": 0,
      "slot": 0
    },
    {
      "id": -1,
      "amount": 0,
      "slot": 0
    },
    {
      "id": -1,
      "amount": 0,
      "slot": 0
    },
    {
      "id": -1,
      "amount": 0,
      "slot": 0
    },
    {
      "id": -1,
      "amount": 0,
      "slot": 0
    },
    {
      "id": -1,
      "amount": 0,
      "slot": 0
    },
    {
      "id": -1,
      "amount": 0,
      "slot": 0
    },
    {
      "id": -1,
      "amount": 0,
      "slot": 0
    },
    {
      "id": -1,
      "amount": 0,
      "slot": 0
    },
    {
      "id": -1,
      "amount": 0,
      "slot": 0
    },
    {
      "id": -1,
      "amount": 0,
      "slot": 0
    },
    {
      "id": -1,
      "amount": 0,
      "slot": 0
    },
    {
      "id": -1,
      "amount": 0,
      "slot": 0
    }
  ],
  "bank-0": [
    {
      "id": 8851,
      "amount": 501,
      "slot": 0
    },
    {
      "id": 1621,
      "amount": 1,
      "slot": 0
    },
    {
      "id": 995,
      "amount": 45174,
      "slot": 0
    },
    {
      "id": 532,
      "amount": 1,
      "slot": 0
    },
    {
      "id": 215,
      "amount": 1,
      "slot": 0
    },
    {
      "id": 18349,
      "amount": 1,
      "slot": 0
    },
    {
      "id": 18357,
      "amount": 1,
      "slot": 0
    },
    {
      "id": 6585,
      "amount": 1,
      "slot": 0
    },
    {
      "id": 19786,
      "amount": 1,
      "slot": 0
    },
    {
      "id": 19785,
      "amount": 1,
      "slot": 0
    },
    {
      "id": 11664,
      "amount": 1,
      "slot": 0
    },
    {
      "id": 10499,
      "amount": 1,
      "slot": 0
    },
    {
      "id": 4151,
      "amount": 1,
      "slot": 0
    },
    {
      "id": 8842,
      "amount": 1,
      "slot": 0
    },
    {
      "id": 11732,
      "amount": 1,
      "slot": 0
    },
    {
      "id": 15019,
      "amount": 1,
      "slot": 0
    },
    {
      "id": 9244,
      "amount": 499,
      "slot": 0
    },
    {
      "id": 12093,
      "amount": 25,
      "slot": 0
    }
  ],
  "bank-1": [],
  "bank-2": [],
  "bank-3": [],
  "bank-4": [],
  "bank-5": [],
  "bank-6": [],
  "bank-7": [],
  "bank-8": [],
  "ge-slots": [
    {
      "state": "EMPTY"
    },
    {
      "state": "EMPTY"
    },
    {
      "state": "EMPTY"
    },
    {
      "state": "EMPTY"
    },
    {
      "state": "EMPTY"
    },
    {
      "state": "EMPTY"
    }
  ],
  "charm-imp": [
    0,
    0,
    0,
    0
  ],
  "friends": [
    39435
  ],
  "ignores": [],
  "loyalty-titles": [
    false,
    false,
    false,
    false,
    false,
    true,
    true,
    true,
    false,
    false,
    false,
    false
  ],
  "kills": [
    {
      "npcName": "Zombie",
      "amount": 35,
      "boss": false
    },
    {
      "npcName": "Rock Crab",
      "amount": 22,
      "boss": false
    },
    {
      "npcName": "Cyclops",
      "amount": 1,
      "boss": false
    },
    {
      "npcName": "Man",
      "amount": 22,
      "boss": false
    },
    {
      "npcName": "Venenatis",
      "amount": 1,
      "boss": true
    },
    {
      "npcName": "Vet\u0027ion",
      "amount": 1,
      "boss": true
    },
    {
      "npcName": "Callisto",
      "amount": 9,
      "boss": true
    },
    {
      "npcName": "Scorpia",
      "amount": 3,
      "boss": true
    }
  ],
  "drops": [
    {
      "item": 532,
      "amount": 15,
      "rareDrop": false
    },
    {
      "item": 995,
      "amount": 87537,
      "rareDrop": false
    },
    {
      "item": 1621,
      "amount": 1,
      "rareDrop": false
    },
    {
      "item": 215,
      "amount": 2,
      "rareDrop": false
    },
    {
      "item": 12160,
      "amount": 13,
      "rareDrop": false
    },
    {
      "item": 12158,
      "amount": 41,
      "rareDrop": false
    },
    {
      "item": 830,
      "amount": 3,
      "rareDrop": false
    },
    {
      "item": 407,
      "amount": 4,
      "rareDrop": false
    },
    {
      "item": 12163,
      "amount": 7,
      "rareDrop": false
    },
    {
      "item": 1625,
      "amount": 3,
      "rareDrop": false
    },
    {
      "item": 437,
      "amount": 2,
      "rareDrop": false
    },
    {
      "item": 805,
      "amount": 1,
      "rareDrop": false
    },
    {
      "item": 526,
      "amount": 22,
      "rareDrop": false
    },
    {
      "item": 441,
      "amount": 3,
      "rareDrop": false
    },
    {
      "item": 12159,
      "amount": 3,
      "rareDrop": false
    },
    {
      "item": 25,
      "amount": 2,
      "rareDrop": false
    },
    {
      "item": 403,
      "amount": 3,
      "rareDrop": false
    },
    {
      "item": 15188,
      "amount": 1,
      "rareDrop": false
    },
    {
      "item": 562,
      "amount": 2,
      "rareDrop": false
    },
    {
      "item": 556,
      "amount": 3,
      "rareDrop": false
    },
    {
      "item": 7158,
      "amount": 1,
      "rareDrop": true
    },
    {
      "item": 554,
      "amount": 6,
      "rareDrop": false
    },
    {
      "item": 436,
      "amount": 1,
      "rareDrop": false
    },
    {
      "item": 861,
      "amount": 3,
      "rareDrop": false
    },
    {
      "item": 3025,
      "amount": 5,
      "rareDrop": false
    },
    {
      "item": 264,
      "amount": 10,
      "rareDrop": false
    },
    {
      "item": 2,
      "amount": 450,
      "rareDrop": false
    },
    {
      "item": 5300,
      "amount": 3,
      "rareDrop": false
    },
    {
      "item": 226,
      "amount": 40,
      "rareDrop": false
    },
    {
      "item": 1249,
      "amount": 1,
      "rareDrop": false
    },
    {
      "item": 1750,
      "amount": 10,
      "rareDrop": false
    },
    {
      "item": 1139,
      "amount": 1,
      "rareDrop": false
    },
    {
      "item": 199,
      "amount": 1,
      "rareDrop": false
    }
  ],
  "achievements-completion": [
    false,
    false,
    false,
    false,
    false,
    false,
    false,
    false,
    false,
    false,
    false,
    false,
    false,
    true,
    false,
    false,
    false,
    false,
    false,
    false,
    true,
    true,
    false,
    true,
    true,
    true,
    true,
    true,
    false,
    false,
    false,
    false,
    false,
    false,
    false,
    false,
    false,
    false,
    false,
    false,
    false,
    false,
    false,
    false,
    false,
    false,
    false,
    false,
    false,
    false,
    false,
    true,
    false,
    false,
    false,
    false,
    false,
    false,
    false,
    false,
    false,
    false,
    false,
    false,
    false,
    false,
    false,
    false,
    false,
    false,
    false,
    false,
    false,
    false,
    false,
    false,
    false,
    false,
    false,
    false,
    false,
    false,
    false,
    false,
    false,
    false,
    false,
    false,
    false,
    false,
    false,
    false,
    false,
    false,
    false,
    false,
    false,
    false,
    false,
    false,
    false
  ],
  "achievements-progress": [
    968,
    830,
    723,
    0,
    0,
    0,
    0,
    0,
    0,
    0,
    0,
    0,
    0,
    0,
    0,
    0,
    0,
    12,
    0,
    0,
    30,
    88626,
    5107,
    10912,
    0,
    0,
    0,
    0,
    0,
    0,
    0,
    0,
    0,
    0,
    0,
    0,
    0,
    0,
    0,
    0,
    30,
    0,
    0,
    475483,
    5107,
    10912,
    0,
    0,
    0,
    94,
    14,
    0,
    3
  ]
}